{
  "id": "arch_cpu_troubleshooting",
  "title": "CPU Performance Troubleshooting",
  "source": {
    "name": "Arch Wiki",
    "url": "https://wiki.archlinux.org/title/Improving_performance"
  },
  "os": "linux",
  "distro": "arch",
  "category": "cpu",
  "confidence": "high",
  "tags": ["cpu", "performance", "troubleshooting"],
  "content": {
    "symptoms": [
      "System feels slow",
      "High CPU usage at idle"
    ],
    "causes": [
      "Background services consuming CPU",
      "Incorrect power management settings"
    ],
    "diagnosis": [
      "Identify CPU-hogging processes",
      "Check CPU frequency behavior"
    ],
    "solutions": [
      "Disable unnecessary services",
      "Tune CPU governor",
      "Check for runaway processes"
    ],
    "commands": [
      "top",
      "htop",
      "ps aux --sort=-%cpu"
    ],
    "notes": "Always identify the process before applying system-wide fixes."
  }
}
